odoo/addons/test_connector/README.rst
odoo/addons/test_connector/__init__.py
odoo/addons/test_connector/__manifest__.py
odoo/addons/test_connector/i18n/am.po
odoo/addons/test_connector/i18n/ca.po
odoo/addons/test_connector/i18n/de.po
odoo/addons/test_connector/i18n/el_GR.po
odoo/addons/test_connector/i18n/es.po
odoo/addons/test_connector/i18n/es_ES.po
odoo/addons/test_connector/i18n/fi.po
odoo/addons/test_connector/i18n/fr.po
odoo/addons/test_connector/i18n/gl.po
odoo/addons/test_connector/i18n/hu.po
odoo/addons/test_connector/i18n/it.po
odoo/addons/test_connector/i18n/nl.po
odoo/addons/test_connector/i18n/pt.po
odoo/addons/test_connector/i18n/pt_BR.po
odoo/addons/test_connector/i18n/pt_PT.po
odoo/addons/test_connector/i18n/sl.po
odoo/addons/test_connector/i18n/test_connector.pot
odoo/addons/test_connector/i18n/tr.po
odoo/addons/test_connector/i18n/zh_CN.po
odoo/addons/test_connector/models/__init__.py
odoo/addons/test_connector/models/components.py
odoo/addons/test_connector/models/models.py
odoo/addons/test_connector/readme/CONTRIBUTORS.rst
odoo/addons/test_connector/readme/DESCRIPTION.rst
odoo/addons/test_connector/security/ir.model.access.csv
odoo/addons/test_connector/static/description/icon.png
odoo/addons/test_connector/static/description/index.html
odoo/addons/test_connector/tests/__init__.py
odoo/addons/test_connector/tests/test_default_binder.py
odoo/addons/test_connector/tests/test_related_action_binding.py
odoo13_addon_test_connector-13.0.1.0.1.dev7.dist-info/METADATA
odoo13_addon_test_connector-13.0.1.0.1.dev7.dist-info/WHEEL
odoo13_addon_test_connector-13.0.1.0.1.dev7.dist-info/top_level.txt
odoo13_addon_test_connector-13.0.1.0.1.dev7.dist-info/RECORD
