Metadata-Version: 2.1
Name: odoo13-addon-test-connector
Version: 13.0.1.0.1.dev7
Summary: Automated tests for Connector, do not install.
Home-page: http://odoo-connector.com
Author: Camptocamp,Odoo Community Association (OCA)
Author-email: support@odoo-community.org
License: LGPL-3
Platform: UNKNOWN
Classifier: Programming Language :: Python
Classifier: Framework :: Odoo
Classifier: Framework :: Odoo :: 13.0
Classifier: License :: OSI Approved :: GNU Lesser General Public License v3 (LGPLv3)
Requires-Python: >=3.5
Requires-Dist: odoo13-addon-connector
Requires-Dist: odoo <13.1dev,>=13.0a
